many_toon_cli/__init__.py
many_toon_cli/manga.py
many_toon_cli-0.1.8.dist-info/LICENSE
many_toon_cli-0.1.8.dist-info/METADATA
many_toon_cli-0.1.8.dist-info/WHEEL
many_toon_cli-0.1.8.dist-info/entry_points.txt
many_toon_cli-0.1.8.dist-info/top_level.txt
many_toon_cli-0.1.8.dist-info/RECORD
