Metadata-Version: 2.1
Name: many-toon-cli
Version: 0.1.8
Summary: A CLI tool for interacting with manga sites asynchronously and downloading 18+ manhwa
Home-page: https://github.com/Kamanati/many-toon-cli
Author: hasanfq
Author-email: hasanfq818@gmail.com
Classifier: Programming Language :: Python :: 3
Classifier: License :: OSI Approved :: MIT License
Classifier: Operating System :: OS Independent
Requires-Python: >=3.8
License-File: LICENSE
Requires-Dist: aiohttp >=3.8.0
Requires-Dist: beautifulsoup4 >=4.9.3
Requires-Dist: tqdm >=4.62.3
Requires-Dist: pillow >=8.3.1
Requires-Dist: fpdf >=1.7.2
Requires-Dist: argparse >=1.4.0
